setup.py
django_softdeletev2.egg-info/PKG-INFO
django_softdeletev2.egg-info/SOURCES.txt
django_softdeletev2.egg-info/dependency_links.txt
django_softdeletev2.egg-info/requires.txt
django_softdeletev2.egg-info/top_level.txt
softdelete/__init__.py
softdelete/forms.py
softdelete/models.py
softdelete/settings.py
softdelete/signals.py
softdelete/urls.py
softdelete/views.py
softdelete/admin/__init__.py
softdelete/admin/admin.py
softdelete/admin/forms.py
softdelete/migrations/0001_initial.py
softdelete/migrations/__init__.py
softdelete/south_migrations/0001_initial.py
softdelete/south_migrations/0002_auto__del_recordset__del_unique_recordset_changeset_content_type_objec.py
softdelete/south_migrations/0003_auto__chg_field_softdeleterecord_object_id__chg_field_changeset_object.py
softdelete/south_migrations/__init__.py
softdelete/test_softdelete_app/__init__.py
softdelete/test_softdelete_app/models.py
softdelete/tests/__init__.py
softdelete/tests/test_sd.py
softdelete/tests/test_views.py