Metadata-Version: 1.1
Name: django-softdeletev2
Version: 0.4.2
Summary: Soft delete support for Django ORM, with undelete.
Home-page: https://github.com/galacticsurfer/django-softdelete
Author: Steve Coursen
Author-email: sachin.prabhu@kuliza.com
License: UNKNOWN
Platform: UNKNOWN
Classifier: Framework :: Django
Classifier: License :: OSI Approved :: BSD License
Classifier: Environment :: Web Environment
